odoo9_addon_website_sale_default_country-9.0.1.0.0-py2.7-nspkg.pth
odoo_addons/website_sale_default_country/__openerp__.py
odoo_addons/website_sale_default_country/__init__.py
odoo_addons/website_sale_default_country/README.rst
odoo_addons/website_sale_default_country/controllers/main.py
odoo_addons/website_sale_default_country/controllers/__init__.py
odoo_addons/website_sale_default_country/static/description/icon.png
odoo9_addon_website_sale_default_country-9.0.1.0.0.dist-info/top_level.txt
odoo9_addon_website_sale_default_country-9.0.1.0.0.dist-info/WHEEL
odoo9_addon_website_sale_default_country-9.0.1.0.0.dist-info/RECORD
odoo9_addon_website_sale_default_country-9.0.1.0.0.dist-info/metadata.json
odoo9_addon_website_sale_default_country-9.0.1.0.0.dist-info/DESCRIPTION.rst
odoo9_addon_website_sale_default_country-9.0.1.0.0.dist-info/METADATA
odoo9_addon_website_sale_default_country-9.0.1.0.0.dist-info/namespace_packages.txt
